smtb/__init__.py
smtb/smtb.py
smtb-0.0.0.0.20240209.1.dist-info/METADATA
smtb-0.0.0.0.20240209.1.dist-info/WHEEL
smtb-0.0.0.0.20240209.1.dist-info/entry_points.txt
smtb-0.0.0.0.20240209.1.dist-info/licenses/LICENSE
smtb-0.0.0.0.20240209.1.dist-info/RECORD
