Metadata-Version: 2.1
Name: smtb
Version: 0.0.0.0.20240209.1
Summary: Python Module for Sumitomo Mitsui Trust Bank
Project-URL: Homepage, https://github.com/KuboFukuichiro/PySMTB
Project-URL: Documentation, https://github.com/KuboFukuichiro/PySMTB/doc
Project-URL: Repository, https://github.com/KuboFukuichiro/PySMTB
Author: Fukuichiro Kubo
Maintainer: Fukuichiro Kubo
License: MIT License
License-File: LICENSE
Keywords: stem
Classifier: Development Status :: 4 - Beta
Classifier: Programming Language :: Python
Requires-Python: >=3.8
Requires-Dist: numpy
Requires-Dist: pandas
Provides-Extra: cli
Requires-Dist: click; extra == 'cli'
Requires-Dist: rich; extra == 'cli'
Provides-Extra: gui
Requires-Dist: pyqt5; extra == 'gui'
